cookiecutter_packages_automate_pypi/__init__.py
cookiecutter_packages_automate_pypi/common.py
cookiecutter_packages_automate_pypi/cookiecutter_packages_automate_pypi.py
cookiecutter_packages_automate_pypi-0.0.2.dist-info/LICENSE
cookiecutter_packages_automate_pypi-0.0.2.dist-info/METADATA
cookiecutter_packages_automate_pypi-0.0.2.dist-info/WHEEL
cookiecutter_packages_automate_pypi-0.0.2.dist-info/entry_points.txt
cookiecutter_packages_automate_pypi-0.0.2.dist-info/top_level.txt
cookiecutter_packages_automate_pypi-0.0.2.dist-info/RECORD
