Metadata-Version: 2.2
Name: cookiecutter-packages-automate-PyPI
Version: 0.0.2
Summary: A demo for building python packages using cookiecutter and update automatically via GitHub Actions, with version management through bump-my-version
Author-email: ZiyeLi <liziye725@gmail.com>
License: MIT License
Project-URL: Homepage, https://github.com/Liziye725/cookiecutter-packages-automate-PyPI
Keywords: cookiecutter-packages-automate-PyPI
Classifier: Intended Audience :: Developers
Classifier: License :: OSI Approved :: MIT License
Classifier: Natural Language :: English
Classifier: Programming Language :: Python :: 3.8
Classifier: Programming Language :: Python :: 3.9
Classifier: Programming Language :: Python :: 3.10
Classifier: Programming Language :: Python :: 3.11
Classifier: Programming Language :: Python :: 3.12
Requires-Python: >=3.8
License-File: LICENSE
Requires-Dist: numpy
Provides-Extra: all
Requires-Dist: cookiecutter-packages-automate-PyPI[extra]; extra == "all"
Provides-Extra: extra
Requires-Dist: pandas; extra == "extra"
